axisfuzzy/__init__.py
axisfuzzy/__init__.pyi
axisfuzzy/version.py
axisfuzzy/analysis/__init__.py
axisfuzzy/analysis/__init__.pyi
axisfuzzy/analysis/accessor.py
axisfuzzy/analysis/build_in.py
axisfuzzy/analysis/pipeline.py
axisfuzzy/analysis/app/__init__.py
axisfuzzy/analysis/app/model.py
axisfuzzy/analysis/component/__init__.py
axisfuzzy/analysis/component/base.py
axisfuzzy/analysis/component/basic.py
axisfuzzy/analysis/contracts/__init__.py
axisfuzzy/analysis/contracts/base.py
axisfuzzy/analysis/contracts/decorator.py
axisfuzzy/analysis/dataframe/__init__.py
axisfuzzy/analysis/dataframe/frame.py
axisfuzzy/config/__init__.py
axisfuzzy/config/__init__.pyi
axisfuzzy/config/api.py
axisfuzzy/config/api.pyi
axisfuzzy/config/config_file.py
axisfuzzy/config/manager.py
axisfuzzy/core/__init__.py
axisfuzzy/core/__init__.pyi
axisfuzzy/core/backend.py
axisfuzzy/core/base.py
axisfuzzy/core/cache.py
axisfuzzy/core/dispatcher.py
axisfuzzy/core/factory.py
axisfuzzy/core/fuzzarray.py
axisfuzzy/core/fuzzarray.pyi
axisfuzzy/core/fuzznums.py
axisfuzzy/core/fuzznums.pyi
axisfuzzy/core/operation.py
axisfuzzy/core/registry.py
axisfuzzy/core/registry.pyi
axisfuzzy/core/triangular.py
axisfuzzy/extension/__init__.py
axisfuzzy/extension/__init__.pyi
axisfuzzy/extension/decorator.py
axisfuzzy/extension/decorator.pyi
axisfuzzy/extension/dispatcher.py
axisfuzzy/extension/dispatcher.pyi
axisfuzzy/extension/injector.py
axisfuzzy/extension/registry.py
axisfuzzy/fuzzifier/__init__.py
axisfuzzy/fuzzifier/__init__.pyi
axisfuzzy/fuzzifier/fuzzifier.py
axisfuzzy/fuzzifier/fuzzifier.pyi
axisfuzzy/fuzzifier/registry.py
axisfuzzy/fuzzifier/strategy.py
axisfuzzy/fuzztype/__init__.py
axisfuzzy/fuzztype/fs/__init__.py
axisfuzzy/fuzztype/fs/backend.py
axisfuzzy/fuzztype/fs/extension.py
axisfuzzy/fuzztype/fs/fn.py
axisfuzzy/fuzztype/fs/fuzzification.py
axisfuzzy/fuzztype/fs/op.py
axisfuzzy/fuzztype/fs/random.py
axisfuzzy/fuzztype/fs/ext/__init__.py
axisfuzzy/fuzztype/fs/ext/constructor.py
axisfuzzy-0.1.7.dist-info/licenses/LICENSE
axisfuzzy-0.1.7.dist-info/METADATA
axisfuzzy-0.1.7.dist-info/WHEEL
axisfuzzy-0.1.7.dist-info/top_level.txt
axisfuzzy-0.1.7.dist-info/RECORD
