Metadata-Version: 2.4
Name: axisfuzzy
Version: 0.1.7
Summary: A high-performance Python library for fuzzy number and fuzzy array computations
Requires-Python: >=3.12
License-File: LICENSE
Requires-Dist: numpy>=2.2.6
Requires-Dist: numba>=0.61.2
Provides-Extra: analysis
Requires-Dist: pandas>=2.3.2; extra == "analysis"
Requires-Dist: pandas-stubs==2.3.0.250703; extra == "analysis"
Requires-Dist: matplotlib>=3.10.5; extra == "analysis"
Requires-Dist: networkx>=3.0; extra == "analysis"
Requires-Dist: pydot>=1.4.0; extra == "analysis"
Provides-Extra: dev
Requires-Dist: pytest>=8.4.1; extra == "dev"
Requires-Dist: notebook>=7.4.5; extra == "dev"
Provides-Extra: docs
Requires-Dist: sphinx>=7.0.0; extra == "docs"
Requires-Dist: sphinx-copybutton>=0.5.0; extra == "docs"
Requires-Dist: sphinx-design>=0.5.0; extra == "docs"
Requires-Dist: sphinx-autodoc-typehints>=3.0; extra == "docs"
Requires-Dist: sphinx-tabs>=3.4.0; extra == "docs"
Requires-Dist: myst-parser>=2.0.0; extra == "docs"
Requires-Dist: babel>=2.14.0; extra == "docs"
Requires-Dist: sphinx-rtd-theme>=2.0.0; extra == "docs"
Provides-Extra: all
Requires-Dist: axisfuzzy[analysis]; extra == "all"
Requires-Dist: axisfuzzy[dev]; extra == "all"
Requires-Dist: axisfuzzy[docs]; extra == "all"
Dynamic: license-file
